[
  {
    "org": "ZeitOnline",
    "repo_name": "zeit.care",
    "full_name": "ZeitOnline/zeit.care",
    "id": 5338205,
    "login": "kabbeck",
    "user_name": null,
    "contributions": 23
  },
  {
    "org": "ZeitOnline",
    "repo_name": "zeit.care",
    "full_name": "ZeitOnline/zeit.care",
    "id": 5547971,
    "login": "zon-hoppe",
    "user_name": null,
    "contributions": 14
  },
  {
    "org": "ZeitOnline",
    "repo_name": "zeit.care",
    "full_name": "ZeitOnline/zeit.care",
    "id": 577891,
    "login": "wosc",
    "user_name": "Wolfgang Schnerring",
    "contributions": 14
  },
  {
    "org": "ZeitOnline",
    "repo_name": "zeit.care",
    "full_name": "ZeitOnline/zeit.care",
    "id": 193743,
    "login": "rdrongow",
    "user_name": null,
    "contributions": 7
  },
  {
    "org": "ZeitOnline",
    "repo_name": "zeit.care",
    "full_name": "ZeitOnline/zeit.care",
    "id": 1429369,
    "login": "thomasbaumann",
    "user_name": null,
    "contributions": 1
  }
]
