[
  {
    "org": "ZeitOnline",
    "repo_name": "zeit.vgwort",
    "full_name": "ZeitOnline/zeit.vgwort",
    "id": 577891,
    "login": "wosc",
    "user_name": "Wolfgang Schnerring",
    "contributions": 117
  },
  {
    "org": "ZeitOnline",
    "repo_name": "zeit.vgwort",
    "full_name": "ZeitOnline/zeit.vgwort",
    "id": 518288,
    "login": "florianpilz",
    "user_name": "Florian Pilz",
    "contributions": 1
  },
  {
    "org": "ZeitOnline",
    "repo_name": "zeit.vgwort",
    "full_name": "ZeitOnline/zeit.vgwort",
    "id": 1344744,
    "login": "sweh",
    "user_name": "Sebastian Wehrmann",
    "contributions": 1
  },
  {
    "org": "ZeitOnline",
    "repo_name": "zeit.vgwort",
    "full_name": "ZeitOnline/zeit.vgwort",
    "id": 17002572,
    "login": "sallner",
    "user_name": "Steffen Allner",
    "contributions": 1
  }
]
