[
  {
    "org": "OrlandoSentinel",
    "repo_name": "tabs-on-tally-hackathon",
    "full_name": "OrlandoSentinel/tabs-on-tally-hackathon",
    "id": 4754686,
    "login": "charlesminshew",
    "user_name": "Charles Minshew",
    "contributions": 5
  },
  {
    "org": "OrlandoSentinel",
    "repo_name": "tabs-on-tally-hackathon",
    "full_name": "OrlandoSentinel/tabs-on-tally-hackathon",
    "id": 2243202,
    "login": "AndrewGibson27",
    "user_name": "Andrew Gibson",
    "contributions": 2
  }
]
