[
  {
    "org": "seattletimes",
    "repo_name": "mariners-season-tracker",
    "full_name": "seattletimes/mariners-season-tracker",
    "id": 12566233,
    "login": "squinton6188",
    "user_name": null,
    "contributions": 17
  },
  {
    "org": "seattletimes",
    "repo_name": "mariners-season-tracker",
    "full_name": "seattletimes/mariners-season-tracker",
    "id": 13368821,
    "login": "neatonseatimes",
    "user_name": null,
    "contributions": 16
  },
  {
    "org": "seattletimes",
    "repo_name": "mariners-season-tracker",
    "full_name": "seattletimes/mariners-season-tracker",
    "id": 881329,
    "login": "thomaswilburn",
    "user_name": "Thomas Wilburn",
    "contributions": 10
  },
  {
    "org": "seattletimes",
    "repo_name": "mariners-season-tracker",
    "full_name": "seattletimes/mariners-season-tracker",
    "id": 11972166,
    "login": "vnessamartinez",
    "user_name": "Vanessa Martinez",
    "contributions": 7
  },
  {
    "org": "seattletimes",
    "repo_name": "mariners-season-tracker",
    "full_name": "seattletimes/mariners-season-tracker",
    "id": 24574151,
    "login": "ewebeck",
    "user_name": null,
    "contributions": 7
  }
]
