[
  {
    "org": "seattletimes",
    "repo_name": "parallax-template",
    "full_name": "seattletimes/parallax-template",
    "id": 881329,
    "login": "thomaswilburn",
    "user_name": "Thomas Wilburn",
    "contributions": 13
  },
  {
    "org": "seattletimes",
    "repo_name": "parallax-template",
    "full_name": "seattletimes/parallax-template",
    "id": 24574151,
    "login": "ewebeck",
    "user_name": null,
    "contributions": 3
  },
  {
    "org": "seattletimes",
    "repo_name": "parallax-template",
    "full_name": "seattletimes/parallax-template",
    "id": 1236790,
    "login": "martgnz",
    "user_name": "Mart\u00edn Gonz\u00e1lez G\u00f3mez",
    "contributions": 1
  },
  {
    "org": "seattletimes",
    "repo_name": "parallax-template",
    "full_name": "seattletimes/parallax-template",
    "id": 13368821,
    "login": "neatonseatimes",
    "user_name": null,
    "contributions": 1
  }
]
