[
  {
    "org": "coralproject",
    "repo_name": "talk",
    "full_name": "coralproject/talk",
    "id": 5751504,
    "login": "nick-funk",
    "user_name": "Nick Funk",
    "contributions": 1125
  },
  {
    "org": "coralproject",
    "repo_name": "talk",
    "full_name": "coralproject/talk",
    "id": 6287012,
    "login": "kabeaty",
    "user_name": "Kathryn Beaty",
    "contributions": 913
  },
  {
    "org": "coralproject",
    "repo_name": "talk",
    "full_name": "coralproject/talk",
    "id": 1789029,
    "login": "tessalt",
    "user_name": "Tessa Thornton",
    "contributions": 799
  },
  {
    "org": "coralproject",
    "repo_name": "talk",
    "full_name": "coralproject/talk",
    "id": 14221600,
    "login": "cvle",
    "user_name": "Vinh",
    "contributions": 707
  },
  {
    "org": "coralproject",
    "repo_name": "talk",
    "full_name": "coralproject/talk",
    "id": 633002,
    "login": "wyattjoh",
    "user_name": "Wyatt Johnson",
    "contributions": 535
  },
  {
    "org": "coralproject",
    "repo_name": "talk",
    "full_name": "coralproject/talk",
    "id": 15076708,
    "login": "marcushaddon",
    "user_name": "Marcus Haddon",
    "contributions": 411
  },
  {
    "org": "coralproject",
    "repo_name": "talk",
    "full_name": "coralproject/talk",
    "id": 1401559,
    "login": "okbel",
    "user_name": "Bel",
    "contributions": 288
  },
  {
    "org": "coralproject",
    "repo_name": "talk",
    "full_name": "coralproject/talk",
    "id": 3925948,
    "login": "iambrianchan",
    "user_name": "Brian Chan",
    "contributions": 62
  },
  {
    "org": "coralproject",
    "repo_name": "talk",
    "full_name": "coralproject/talk",
    "id": 1077300,
    "login": "kgardnr",
    "user_name": "Kim Gardner",
    "contributions": 37
  },
  {
    "org": "coralproject",
    "repo_name": "talk",
    "full_name": "coralproject/talk",
    "id": 3017969,
    "login": "dkolkena",
    "user_name": "Daniel Kolkena",
    "contributions": 33
  },
  {
    "org": "coralproject",
    "repo_name": "talk",
    "full_name": "coralproject/talk",
    "id": 49699333,
    "login": "dependabot[bot]",
    "user_name": null,
    "contributions": 24
  },
  {
    "org": "coralproject",
    "repo_name": "talk",
    "full_name": "coralproject/talk",
    "id": 25023177,
    "login": "cristiandean",
    "user_name": "Cristian Dean",
    "contributions": 22
  },
  {
    "org": "coralproject",
    "repo_name": "talk",
    "full_name": "coralproject/talk",
    "id": 10014755,
    "login": "losowsky",
    "user_name": null,
    "contributions": 17
  },
  {
    "org": "coralproject",
    "repo_name": "talk",
    "full_name": "coralproject/talk",
    "id": 6742496,
    "login": "rmens",
    "user_name": "Raymon Mens",
    "contributions": 13
  },
  {
    "org": "coralproject",
    "repo_name": "talk",
    "full_name": "coralproject/talk",
    "id": 82044999,
    "login": "nbachman-vox",
    "user_name": "Nancy Bachman",
    "contributions": 13
  },
  {
    "org": "coralproject",
    "repo_name": "talk",
    "full_name": "coralproject/talk",
    "id": 6967002,
    "login": "janslu",
    "user_name": "Jan Slusarczyk",
    "contributions": 6
  },
  {
    "org": "coralproject",
    "repo_name": "talk",
    "full_name": "coralproject/talk",
    "id": 46453368,
    "login": "bowser2010",
    "user_name": null,
    "contributions": 6
  },
  {
    "org": "coralproject",
    "repo_name": "talk",
    "full_name": "coralproject/talk",
    "id": 5360796,
    "login": "HectorNM",
    "user_name": "Hector",
    "contributions": 5
  },
  {
    "org": "coralproject",
    "repo_name": "talk",
    "full_name": "coralproject/talk",
    "id": 20875849,
    "login": "samisafatli",
    "user_name": "Sami Safatli",
    "contributions": 5
  },
  {
    "org": "coralproject",
    "repo_name": "talk",
    "full_name": "coralproject/talk",
    "id": 48677536,
    "login": "DimDimDimDimDimDim",
    "user_name": null,
    "contributions": 5
  },
  {
    "org": "coralproject",
    "repo_name": "talk",
    "full_name": "coralproject/talk",
    "id": 5577870,
    "login": "HenkoR",
    "user_name": "HenkoR",
    "contributions": 4
  },
  {
    "org": "coralproject",
    "repo_name": "talk",
    "full_name": "coralproject/talk",
    "id": 9038049,
    "login": "oliver-dvorski",
    "user_name": "Oliver Dvorski",
    "contributions": 4
  },
  {
    "org": "coralproject",
    "repo_name": "talk",
    "full_name": "coralproject/talk",
    "id": 1610227,
    "login": "bennettp123",
    "user_name": "Bennett Perkins",
    "contributions": 3
  },
  {
    "org": "coralproject",
    "repo_name": "talk",
    "full_name": "coralproject/talk",
    "id": 47566939,
    "login": "Lammland",
    "user_name": "Esteban Y\u00e1\u00f1ez Behrens",
    "contributions": 3
  },
  {
    "org": "coralproject",
    "repo_name": "talk",
    "full_name": "coralproject/talk",
    "id": 7496030,
    "login": "immber",
    "user_name": null,
    "contributions": 3
  },
  {
    "org": "coralproject",
    "repo_name": "talk",
    "full_name": "coralproject/talk",
    "id": 8027311,
    "login": "jpkilpi",
    "user_name": null,
    "contributions": 3
  },
  {
    "org": "coralproject",
    "repo_name": "talk",
    "full_name": "coralproject/talk",
    "id": 29153977,
    "login": "ElijahPepe",
    "user_name": "Elijah",
    "contributions": 2
  },
  {
    "org": "coralproject",
    "repo_name": "talk",
    "full_name": "coralproject/talk",
    "id": 45395012,
    "login": "tselmek",
    "user_name": "Antoine J\u00e9sus",
    "contributions": 2
  },
  {
    "org": "coralproject",
    "repo_name": "talk",
    "full_name": "coralproject/talk",
    "id": 1230714,
    "login": "miroc",
    "user_name": "Miroslav Svitok",
    "contributions": 2
  },
  {
    "org": "coralproject",
    "repo_name": "talk",
    "full_name": "coralproject/talk",
    "id": 1783541,
    "login": "bastiankistner",
    "user_name": "Bastian Kistner",
    "contributions": 2
  },
  {
    "org": "coralproject",
    "repo_name": "talk",
    "full_name": "coralproject/talk",
    "id": 8798149,
    "login": "Dzarr",
    "user_name": null,
    "contributions": 2
  },
  {
    "org": "coralproject",
    "repo_name": "talk",
    "full_name": "coralproject/talk",
    "id": 14968783,
    "login": "Emptyfruit",
    "user_name": "Maxim Reznitskiy",
    "contributions": 2
  },
  {
    "org": "coralproject",
    "repo_name": "talk",
    "full_name": "coralproject/talk",
    "id": 145166369,
    "login": "taisglobo",
    "user_name": "Ta\u00eds Ara\u00fajo",
    "contributions": 1
  },
  {
    "org": "coralproject",
    "repo_name": "talk",
    "full_name": "coralproject/talk",
    "id": 5403342,
    "login": "ilyaTT",
    "user_name": null,
    "contributions": 1
  },
  {
    "org": "coralproject",
    "repo_name": "talk",
    "full_name": "coralproject/talk",
    "id": 869002,
    "login": "happylewie",
    "user_name": null,
    "contributions": 1
  },
  {
    "org": "coralproject",
    "repo_name": "talk",
    "full_name": "coralproject/talk",
    "id": 1596276,
    "login": "tmair",
    "user_name": null,
    "contributions": 1
  },
  {
    "org": "coralproject",
    "repo_name": "talk",
    "full_name": "coralproject/talk",
    "id": 88420799,
    "login": "ddrysdale-ffx",
    "user_name": null,
    "contributions": 1
  },
  {
    "org": "coralproject",
    "repo_name": "talk",
    "full_name": "coralproject/talk",
    "id": 9404975,
    "login": "ant1fr",
    "user_name": "ant1",
    "contributions": 1
  },
  {
    "org": "coralproject",
    "repo_name": "talk",
    "full_name": "coralproject/talk",
    "id": 483060,
    "login": "yonran",
    "user_name": "Yonathan Randolph",
    "contributions": 1
  },
  {
    "org": "coralproject",
    "repo_name": "talk",
    "full_name": "coralproject/talk",
    "id": 55574354,
    "login": "walissoncom",
    "user_name": "Walisson Rodrigues",
    "contributions": 1
  },
  {
    "org": "coralproject",
    "repo_name": "talk",
    "full_name": "coralproject/talk",
    "id": 73962379,
    "login": "thomasender",
    "user_name": "Thomas Ender",
    "contributions": 1
  },
  {
    "org": "coralproject",
    "repo_name": "talk",
    "full_name": "coralproject/talk",
    "id": 2052340,
    "login": "Sentynel",
    "user_name": "Sam Lade",
    "contributions": 1
  },
  {
    "org": "coralproject",
    "repo_name": "talk",
    "full_name": "coralproject/talk",
    "id": 10260430,
    "login": "desk467",
    "user_name": "Ricardo Gomes",
    "contributions": 1
  },
  {
    "org": "coralproject",
    "repo_name": "talk",
    "full_name": "coralproject/talk",
    "id": 17433156,
    "login": "natastro",
    "user_name": "Natalie",
    "contributions": 1
  },
  {
    "org": "coralproject",
    "repo_name": "talk",
    "full_name": "coralproject/talk",
    "id": 406306,
    "login": "mvdwaeter",
    "user_name": null,
    "contributions": 1
  },
  {
    "org": "coralproject",
    "repo_name": "talk",
    "full_name": "coralproject/talk",
    "id": 694907,
    "login": "mbanusic",
    "user_name": "Marko Banusic",
    "contributions": 1
  },
  {
    "org": "coralproject",
    "repo_name": "talk",
    "full_name": "coralproject/talk",
    "id": 3321655,
    "login": "jacotec",
    "user_name": "Marco Jakobs",
    "contributions": 1
  },
  {
    "org": "coralproject",
    "repo_name": "talk",
    "full_name": "coralproject/talk",
    "id": 55802548,
    "login": "karimbouchouicha",
    "user_name": "Karim Bouchouicha",
    "contributions": 1
  },
  {
    "org": "coralproject",
    "repo_name": "talk",
    "full_name": "coralproject/talk",
    "id": 281236,
    "login": "jukart",
    "user_name": "J\u00fcrgen Kartnaller",
    "contributions": 1
  },
  {
    "org": "coralproject",
    "repo_name": "talk",
    "full_name": "coralproject/talk",
    "id": 11612102,
    "login": "ingriddraagen",
    "user_name": "Ingrid Gormsdatter Draagen",
    "contributions": 1
  },
  {
    "org": "coralproject",
    "repo_name": "talk",
    "full_name": "coralproject/talk",
    "id": 258820,
    "login": "honzie",
    "user_name": "Hans Sprecher",
    "contributions": 1
  },
  {
    "org": "coralproject",
    "repo_name": "talk",
    "full_name": "coralproject/talk",
    "id": 12849807,
    "login": "lusbuab",
    "user_name": "Florian H\u00e4mmerle",
    "contributions": 1
  },
  {
    "org": "coralproject",
    "repo_name": "talk",
    "full_name": "coralproject/talk",
    "id": 15653196,
    "login": "felixdro",
    "user_name": "Felix D",
    "contributions": 1
  },
  {
    "org": "coralproject",
    "repo_name": "talk",
    "full_name": "coralproject/talk",
    "id": 604917,
    "login": "Chavao",
    "user_name": "Diego Chav\u00e3o",
    "contributions": 1
  },
  {
    "org": "coralproject",
    "repo_name": "talk",
    "full_name": "coralproject/talk",
    "id": 2268778,
    "login": "bderen",
    "user_name": "Bogdan Deren",
    "contributions": 1
  },
  {
    "org": "coralproject",
    "repo_name": "talk",
    "full_name": "coralproject/talk",
    "id": 23871115,
    "login": "allanassis",
    "user_name": "Allan Assis",
    "contributions": 1
  },
  {
    "org": "coralproject",
    "repo_name": "talk",
    "full_name": "coralproject/talk",
    "id": 12200062,
    "login": "lxndrblz",
    "user_name": "Alexander Bilz",
    "contributions": 1
  },
  {
    "org": "coralproject",
    "repo_name": "talk",
    "full_name": "coralproject/talk",
    "id": 20671872,
    "login": "RyleySill93",
    "user_name": "Ryley Sill",
    "contributions": 1
  },
  {
    "org": "coralproject",
    "repo_name": "talk",
    "full_name": "coralproject/talk",
    "id": 34183521,
    "login": "rigperro",
    "user_name": "Riku Aapakallio-Autio",
    "contributions": 1
  }
]
