[
  {
    "org": "NUKnightLab",
    "repo_name": "twxplorer",
    "full_name": "NUKnightLab/twxplorer",
    "id": 307713,
    "login": "scott2b",
    "user_name": "Scott Bradley",
    "contributions": 36
  },
  {
    "org": "NUKnightLab",
    "repo_name": "twxplorer",
    "full_name": "NUKnightLab/twxplorer",
    "id": 37711,
    "login": "aaronsalmon",
    "user_name": "Aaron U. Salmon",
    "contributions": 33
  },
  {
    "org": "NUKnightLab",
    "repo_name": "twxplorer",
    "full_name": "NUKnightLab/twxplorer",
    "id": 46313,
    "login": "JoeGermuska",
    "user_name": "Joe Germuska",
    "contributions": 20
  },
  {
    "org": "NUKnightLab",
    "repo_name": "twxplorer",
    "full_name": "NUKnightLab/twxplorer",
    "id": 1273899,
    "login": "knightlab",
    "user_name": null,
    "contributions": 1
  }
]
