[
  {
    "org": "guardian",
    "repo_name": "anghammarad",
    "full_name": "guardian/anghammarad",
    "id": 108136057,
    "login": "gu-scala-steward-public-repos[bot]",
    "user_name": null,
    "contributions": 220
  },
  {
    "org": "guardian",
    "repo_name": "anghammarad",
    "full_name": "guardian/anghammarad",
    "id": 836140,
    "login": "akash1810",
    "user_name": "Akash Askoolum",
    "contributions": 196
  },
  {
    "org": "guardian",
    "repo_name": "anghammarad",
    "full_name": "guardian/anghammarad",
    "id": 29761,
    "login": "adamnfish",
    "user_name": "Adam Fisher",
    "contributions": 126
  },
  {
    "org": "guardian",
    "repo_name": "anghammarad",
    "full_name": "guardian/anghammarad",
    "id": 19384074,
    "login": "jacobwinch",
    "user_name": "Jacob Winch",
    "contributions": 46
  },
  {
    "org": "guardian",
    "repo_name": "anghammarad",
    "full_name": "guardian/anghammarad",
    "id": 49699333,
    "login": "dependabot[bot]",
    "user_name": null,
    "contributions": 26
  },
  {
    "org": "guardian",
    "repo_name": "anghammarad",
    "full_name": "guardian/anghammarad",
    "id": 80390930,
    "login": "JuliaBrigitte",
    "user_name": "Julia Branke",
    "contributions": 18
  },
  {
    "org": "guardian",
    "repo_name": "anghammarad",
    "full_name": "guardian/anghammarad",
    "id": 67543397,
    "login": "NovemberTang",
    "user_name": "Natasha",
    "contributions": 15
  },
  {
    "org": "guardian",
    "repo_name": "anghammarad",
    "full_name": "guardian/anghammarad",
    "id": 21217225,
    "login": "AshCorr",
    "user_name": "AshCorr",
    "contributions": 14
  },
  {
    "org": "guardian",
    "repo_name": "anghammarad",
    "full_name": "guardian/anghammarad",
    "id": 9384003,
    "login": "sookburt",
    "user_name": "Sue Burt",
    "contributions": 14
  },
  {
    "org": "guardian",
    "repo_name": "anghammarad",
    "full_name": "guardian/anghammarad",
    "id": 615085,
    "login": "mchv",
    "user_name": "Mariot Chauvin",
    "contributions": 13
  },
  {
    "org": "guardian",
    "repo_name": "anghammarad",
    "full_name": "guardian/anghammarad",
    "id": 953792,
    "login": "kenoir",
    "user_name": "Robert Kenny",
    "contributions": 13
  },
  {
    "org": "guardian",
    "repo_name": "anghammarad",
    "full_name": "guardian/anghammarad",
    "id": 7239344,
    "login": "michaelwmcnamara",
    "user_name": "Michael McNamara",
    "contributions": 11
  },
  {
    "org": "guardian",
    "repo_name": "anghammarad",
    "full_name": "guardian/anghammarad",
    "id": 8607683,
    "login": "katebee",
    "user_name": "Kate Whalen",
    "contributions": 11
  },
  {
    "org": "guardian",
    "repo_name": "anghammarad",
    "full_name": "guardian/anghammarad",
    "id": 157699227,
    "login": "gu-scala-library-release[bot]",
    "user_name": null,
    "contributions": 10
  },
  {
    "org": "guardian",
    "repo_name": "anghammarad",
    "full_name": "guardian/anghammarad",
    "id": 1064734,
    "login": "desbo",
    "user_name": "Sam Desborough",
    "contributions": 8
  },
  {
    "org": "guardian",
    "repo_name": "anghammarad",
    "full_name": "guardian/anghammarad",
    "id": 52038,
    "login": "rtyley",
    "user_name": "Roberto Tyley",
    "contributions": 6
  },
  {
    "org": "guardian",
    "repo_name": "anghammarad",
    "full_name": "guardian/anghammarad",
    "id": 77005274,
    "login": "joecowton1",
    "user_name": "Joe Cowton",
    "contributions": 4
  },
  {
    "org": "guardian",
    "repo_name": "anghammarad",
    "full_name": "guardian/anghammarad",
    "id": 5476326,
    "login": "aug24",
    "user_name": "Justin Rowles",
    "contributions": 4
  },
  {
    "org": "guardian",
    "repo_name": "anghammarad",
    "full_name": "guardian/anghammarad",
    "id": 7767575,
    "login": "jonathonherbert",
    "user_name": "Jonathon Herbert",
    "contributions": 2
  },
  {
    "org": "guardian",
    "repo_name": "anghammarad",
    "full_name": "guardian/anghammarad",
    "id": 15648334,
    "login": "tjsilver",
    "user_name": "TJ Silver",
    "contributions": 2
  },
  {
    "org": "guardian",
    "repo_name": "anghammarad",
    "full_name": "guardian/anghammarad",
    "id": 41898282,
    "login": "github-actions[bot]",
    "user_name": null,
    "contributions": 2
  },
  {
    "org": "guardian",
    "repo_name": "anghammarad",
    "full_name": "guardian/anghammarad",
    "id": 858402,
    "login": "nicl",
    "user_name": "nic.long",
    "contributions": 2
  },
  {
    "org": "guardian",
    "repo_name": "anghammarad",
    "full_name": "guardian/anghammarad",
    "id": 8754692,
    "login": "jfsoul",
    "user_name": "Jon Soul",
    "contributions": 1
  },
  {
    "org": "guardian",
    "repo_name": "anghammarad",
    "full_name": "guardian/anghammarad",
    "id": 6035518,
    "login": "shtukas",
    "user_name": "Pascal Honor\u00e9",
    "contributions": 1
  },
  {
    "org": "guardian",
    "repo_name": "anghammarad",
    "full_name": "guardian/anghammarad",
    "id": 156913822,
    "login": "gu-dependency-graph-integrator[bot]",
    "user_name": null,
    "contributions": 1
  },
  {
    "org": "guardian",
    "repo_name": "anghammarad",
    "full_name": "guardian/anghammarad",
    "id": 2470816,
    "login": "jharewinton",
    "user_name": "Jon Hare-Winton",
    "contributions": 1
  }
]
