[
  {
    "org": "guardian",
    "repo_name": "cq-source-image-packages",
    "full_name": "guardian/cq-source-image-packages",
    "id": 49699333,
    "login": "dependabot[bot]",
    "user_name": null,
    "contributions": 40
  },
  {
    "org": "guardian",
    "repo_name": "cq-source-image-packages",
    "full_name": "guardian/cq-source-image-packages",
    "id": 15648334,
    "login": "tjsilver",
    "user_name": "TJ Silver",
    "contributions": 23
  },
  {
    "org": "guardian",
    "repo_name": "cq-source-image-packages",
    "full_name": "guardian/cq-source-image-packages",
    "id": 1722550,
    "login": "kelvin-chappell",
    "user_name": null,
    "contributions": 18
  }
]
