[
  {
    "org": "br-data",
    "repo_name": "corona-newsletter-longread",
    "full_name": "br-data/corona-newsletter-longread",
    "id": 1587837,
    "login": "stekhn",
    "user_name": "Steffen K\u00fchne",
    "contributions": 401
  },
  {
    "org": "br-data",
    "repo_name": "corona-newsletter-longread",
    "full_name": "br-data/corona-newsletter-longread",
    "id": 1007187,
    "login": "MichaelKreil",
    "user_name": "Michael Kreil",
    "contributions": 21
  },
  {
    "org": "br-data",
    "repo_name": "corona-newsletter-longread",
    "full_name": "br-data/corona-newsletter-longread",
    "id": 49699333,
    "login": "dependabot[bot]",
    "user_name": null,
    "contributions": 12
  },
  {
    "org": "br-data",
    "repo_name": "corona-newsletter-longread",
    "full_name": "br-data/corona-newsletter-longread",
    "id": 38108896,
    "login": "bayerlse",
    "user_name": "Sebastian Bayerl",
    "contributions": 1
  }
]
