[
  {
    "org": "PublicI",
    "repo_name": "ld203-loader",
    "full_name": "PublicI/ld203-loader",
    "id": 1174162,
    "login": "pratheekrebala",
    "user_name": "Pratheek Rebala",
    "contributions": 16
  },
  {
    "org": "PublicI",
    "repo_name": "ld203-loader",
    "full_name": "PublicI/ld203-loader",
    "id": 1103467,
    "login": "chriszs",
    "user_name": "Chris Zubak-Skees",
    "contributions": 13
  },
  {
    "org": "PublicI",
    "repo_name": "ld203-loader",
    "full_name": "PublicI/ld203-loader",
    "id": 1727065,
    "login": "ltrgoddard",
    "user_name": "Louis Goddard",
    "contributions": 1
  }
]
