[
  {
    "org": "CondeNast",
    "repo_name": "bestfit",
    "full_name": "CondeNast/bestfit",
    "id": 192891,
    "login": "thlorenz",
    "user_name": "Thorsten Lorenz",
    "contributions": 15
  },
  {
    "org": "CondeNast",
    "repo_name": "bestfit",
    "full_name": "CondeNast/bestfit",
    "id": 1215971,
    "login": "gautamarora",
    "user_name": "Gautam Arora",
    "contributions": 2
  },
  {
    "org": "CondeNast",
    "repo_name": "bestfit",
    "full_name": "CondeNast/bestfit",
    "id": 3279272,
    "login": "joewillnyc",
    "user_name": "Joe Williams",
    "contributions": 2
  }
]
