[
  {
    "org": "ft-interactive",
    "repo_name": "perils-of-perception",
    "full_name": "ft-interactive/perils-of-perception",
    "id": 9371095,
    "login": "davidbjourno",
    "user_name": "David Blood",
    "contributions": 96
  },
  {
    "org": "ft-interactive",
    "repo_name": "perils-of-perception",
    "full_name": "ft-interactive/perils-of-perception",
    "id": 125399,
    "login": "tomgp",
    "user_name": "Tom Pearson",
    "contributions": 2
  },
  {
    "org": "ft-interactive",
    "repo_name": "perils-of-perception",
    "full_name": "ft-interactive/perils-of-perception",
    "id": 998519,
    "login": "martinstabe",
    "user_name": "Martin Stabe",
    "contributions": 1
  }
]
