[
  {
    "org": "coralproject",
    "name": "old-coral-project-site",
    "full_name": "coralproject/old-coral-project-site",
    "homepage": "http://coralproject.net/",
    "description": "Old docs for our github pages site, now deprecated.",
    "language": "HTML",
    "created_at": "2014-10-15 20:43:23+00:00",
    "updated_at": "2017-01-20 19:54:54+00:00",
    "pushed_at": "2016-07-26 19:10:40+00:00",
    "fork": false,
    "stargazers_count": 0,
    "watchers_count": 0,
    "forks_count": 1,
    "open_issues_count": 0,
    "license": "Other",
    "topics": []
  },
  {
    "org": "coralproject",
    "name": "core",
    "full_name": "coralproject/core",
    "homepage": "http://coralproject.net/",
    "description": "A collaborative effort to improve communities on news sites through open-source software.",
    "language": "Go",
    "created_at": "2015-09-01 14:43:29+00:00",
    "updated_at": "2022-04-27 01:17:04+00:00",
    "pushed_at": "2016-07-26 19:04:17+00:00",
    "fork": false,
    "stargazers_count": 3,
    "watchers_count": 3,
    "forks_count": 0,
    "open_issues_count": 2,
    "license": "Other",
    "topics": []
  },
  {
    "org": "coralproject",
    "name": "atoll",
    "full_name": "coralproject/atoll",
    "homepage": "",
    "description": "Data analysis pipelines",
    "language": "Python",
    "created_at": "2015-09-24 16:37:32+00:00",
    "updated_at": "2023-10-13 19:10:27+00:00",
    "pushed_at": "2021-03-19 21:53:14+00:00",
    "fork": false,
    "stargazers_count": 11,
    "watchers_count": 11,
    "forks_count": 1,
    "open_issues_count": 2,
    "license": "Other",
    "topics": []
  },
  {
    "org": "coralproject",
    "name": "go-atoll",
    "full_name": "coralproject/go-atoll",
    "homepage": "",
    "description": "Deprecated: go client for atoll",
    "language": "Go",
    "created_at": "2015-09-30 18:50:21+00:00",
    "updated_at": "2017-01-20 19:36:52+00:00",
    "pushed_at": "2016-07-26 19:10:03+00:00",
    "fork": false,
    "stargazers_count": 0,
    "watchers_count": 0,
    "forks_count": 1,
    "open_issues_count": 0,
    "license": "Other",
    "topics": []
  },
  {
    "org": "coralproject",
    "name": "reef",
    "full_name": "coralproject/reef",
    "homepage": "",
    "description": "Concepts, practices and principles",
    "language": "Shell",
    "created_at": "2015-10-03 01:18:19+00:00",
    "updated_at": "2024-10-13 20:59:33+00:00",
    "pushed_at": "2019-02-12 21:27:45+00:00",
    "fork": false,
    "stargazers_count": 62,
    "watchers_count": 62,
    "forks_count": 6,
    "open_issues_count": 9,
    "license": "Other",
    "topics": []
  },
  {
    "org": "coralproject",
    "name": "sponge",
    "full_name": "coralproject/sponge",
    "homepage": null,
    "description": "The import layer will contain strategies for pulling data from existing systems into Coral.",
    "language": "Go",
    "created_at": "2015-10-09 18:01:39+00:00",
    "updated_at": "2023-04-08 14:29:42+00:00",
    "pushed_at": "2016-07-26 18:55:31+00:00",
    "fork": false,
    "stargazers_count": 4,
    "watchers_count": 4,
    "forks_count": 1,
    "open_issues_count": 1,
    "license": "Other",
    "topics": [
      "etl"
    ]
  },
  {
    "org": "coralproject",
    "name": "cay",
    "full_name": "coralproject/cay",
    "homepage": "",
    "description": "Front-end code for Coral community tools",
    "language": "JavaScript",
    "created_at": "2015-10-15 18:02:52+00:00",
    "updated_at": "2023-08-23 11:25:28+00:00",
    "pushed_at": "2017-03-18 19:50:33+00:00",
    "fork": false,
    "stargazers_count": 20,
    "watchers_count": 20,
    "forks_count": 5,
    "open_issues_count": 3,
    "license": "Other",
    "topics": []
  },
  {
    "org": "coralproject",
    "name": "design",
    "full_name": "coralproject/design",
    "homepage": "https://coralproject.github.io/design/",
    "description": "Design process and assets for The Coral Project",
    "language": "HTML",
    "created_at": "2015-10-20 10:38:35+00:00",
    "updated_at": "2023-01-28 09:35:33+00:00",
    "pushed_at": "2016-07-26 19:01:59+00:00",
    "fork": false,
    "stargazers_count": 2,
    "watchers_count": 2,
    "forks_count": 1,
    "open_issues_count": 3,
    "license": "Other",
    "topics": []
  },
  {
    "org": "coralproject",
    "name": "shelf",
    "full_name": "coralproject/shelf",
    "homepage": "",
    "description": "Open source services powering site communities (comments, forms, etc.).",
    "language": "Go",
    "created_at": "2015-11-10 21:43:59+00:00",
    "updated_at": "2023-02-19 06:09:05+00:00",
    "pushed_at": "2017-01-27 14:27:01+00:00",
    "fork": false,
    "stargazers_count": 47,
    "watchers_count": 47,
    "forks_count": 7,
    "open_issues_count": 6,
    "license": "Other",
    "topics": []
  },
  {
    "org": "coralproject",
    "name": "pillar",
    "full_name": "coralproject/pillar",
    "homepage": "",
    "description": "Deprecated: Service layer for the Coral ecosystem",
    "language": "Go",
    "created_at": "2015-12-11 21:16:20+00:00",
    "updated_at": "2020-11-22 17:54:05+00:00",
    "pushed_at": "2016-08-29 18:51:34+00:00",
    "fork": false,
    "stargazers_count": 4,
    "watchers_count": 4,
    "forks_count": 1,
    "open_issues_count": 0,
    "license": "Other",
    "topics": []
  },
  {
    "org": "coralproject",
    "name": "xenia-coral",
    "full_name": "coralproject/xenia-coral",
    "homepage": null,
    "description": "Xenia query sets for the Coral Project",
    "language": null,
    "created_at": "2016-01-25 15:21:05+00:00",
    "updated_at": "2017-01-20 19:38:12+00:00",
    "pushed_at": "2016-07-26 19:06:01+00:00",
    "fork": false,
    "stargazers_count": 0,
    "watchers_count": 0,
    "forks_count": 1,
    "open_issues_count": 0,
    "license": "Other",
    "topics": []
  },
  {
    "org": "coralproject",
    "name": "xenia-driver-js",
    "full_name": "coralproject/xenia-driver-js",
    "homepage": null,
    "description": "A javascript (node and front end) driver for Xenia",
    "language": "JavaScript",
    "created_at": "2016-03-24 16:57:08+00:00",
    "updated_at": "2023-01-28 08:25:41+00:00",
    "pushed_at": "2016-07-26 18:53:55+00:00",
    "fork": false,
    "stargazers_count": 1,
    "watchers_count": 1,
    "forks_count": 1,
    "open_issues_count": 0,
    "license": "Other",
    "topics": []
  },
  {
    "org": "coralproject",
    "name": "ask-docs",
    "full_name": "coralproject/ask-docs",
    "homepage": "https://docs.coralproject.net/ask/",
    "description": "Official Ask Documentation for The Coral Project",
    "language": "CSS",
    "created_at": "2016-04-13 23:31:20+00:00",
    "updated_at": "2024-08-16 15:07:07+00:00",
    "pushed_at": "2019-02-01 00:57:28+00:00",
    "fork": false,
    "stargazers_count": 11,
    "watchers_count": 11,
    "forks_count": 14,
    "open_issues_count": 3,
    "license": "Other",
    "topics": []
  },
  {
    "org": "coralproject",
    "name": "elkhorn",
    "full_name": "coralproject/elkhorn",
    "homepage": "https://docs.coralproject.net",
    "description": "Form composer and embeddable form builder for Ask",
    "language": "JavaScript",
    "created_at": "2016-04-21 17:19:30+00:00",
    "updated_at": "2023-01-28 08:25:41+00:00",
    "pushed_at": "2017-12-11 02:34:11+00:00",
    "fork": false,
    "stargazers_count": 5,
    "watchers_count": 5,
    "forks_count": 3,
    "open_issues_count": 4,
    "license": "Other",
    "topics": []
  },
  {
    "org": "coralproject",
    "name": "cay-native",
    "full_name": "coralproject/cay-native",
    "homepage": null,
    "description": "Mobile native version of cay. Working on Android and iOS, powered by React Native",
    "language": "JavaScript",
    "created_at": "2016-05-05 15:20:29+00:00",
    "updated_at": "2023-01-28 08:25:41+00:00",
    "pushed_at": "2016-07-26 19:00:34+00:00",
    "fork": false,
    "stargazers_count": 2,
    "watchers_count": 2,
    "forks_count": 1,
    "open_issues_count": 0,
    "license": "Other",
    "topics": []
  },
  {
    "org": "coralproject",
    "name": "hackathon",
    "full_name": "coralproject/hackathon",
    "homepage": "http://coralproject.github.io/hackathon",
    "description": "Coral Boilerplate for Hackathon",
    "language": "HTML",
    "created_at": "2016-05-07 03:18:01+00:00",
    "updated_at": "2016-05-07 03:32:42+00:00",
    "pushed_at": "2016-05-07 03:34:16+00:00",
    "fork": true,
    "stargazers_count": 0,
    "watchers_count": 0,
    "forks_count": 1,
    "open_issues_count": 0,
    "license": null,
    "topics": []
  },
  {
    "org": "coralproject",
    "name": "slides",
    "full_name": "coralproject/slides",
    "homepage": null,
    "description": "Slides for Presentation Hackathon",
    "language": "JavaScript",
    "created_at": "2016-05-07 03:34:56+00:00",
    "updated_at": "2023-01-28 08:25:41+00:00",
    "pushed_at": "2016-05-07 12:11:22+00:00",
    "fork": false,
    "stargazers_count": 0,
    "watchers_count": 0,
    "forks_count": 1,
    "open_issues_count": 0,
    "license": "MIT License",
    "topics": []
  },
  {
    "org": "coralproject",
    "name": "comments-lab",
    "full_name": "coralproject/comments-lab",
    "homepage": "",
    "description": "This is the Comments Lab. We built it in 2016 to test out some ideas. Try it at lab.coralproject.net",
    "language": "JavaScript",
    "created_at": "2016-05-07 16:44:45+00:00",
    "updated_at": "2023-01-28 06:25:16+00:00",
    "pushed_at": "2019-01-07 22:03:22+00:00",
    "fork": false,
    "stargazers_count": 7,
    "watchers_count": 7,
    "forks_count": 3,
    "open_issues_count": 12,
    "license": "Other",
    "topics": []
  },
  {
    "org": "coralproject",
    "name": "mongodata",
    "full_name": "coralproject/mongodata",
    "homepage": null,
    "description": null,
    "language": "Shell",
    "created_at": "2016-05-16 19:31:13+00:00",
    "updated_at": "2016-05-16 19:33:19+00:00",
    "pushed_at": "2016-07-28 20:49:09+00:00",
    "fork": false,
    "stargazers_count": 0,
    "watchers_count": 0,
    "forks_count": 1,
    "open_issues_count": 0,
    "license": null,
    "topics": []
  },
  {
    "org": "coralproject",
    "name": "coralproject-site-2016",
    "full_name": "coralproject/coralproject-site-2016",
    "homepage": "https://www.coralproject.net",
    "description": "The Coral Project main website",
    "language": "HTML",
    "created_at": "2016-06-30 15:48:39+00:00",
    "updated_at": "2024-07-08 17:04:28+00:00",
    "pushed_at": "2018-06-04 15:51:23+00:00",
    "fork": false,
    "stargazers_count": 7,
    "watchers_count": 7,
    "forks_count": 6,
    "open_issues_count": 0,
    "license": "Other",
    "topics": []
  },
  {
    "org": "coralproject",
    "name": "ask",
    "full_name": "coralproject/ask",
    "homepage": "https://coralproject.net/products/ask.html",
    "description": "A better way for journalists to manage forms, submissions, and galleries. Because journalism needs everyone.",
    "language": null,
    "created_at": "2016-07-13 14:52:00+00:00",
    "updated_at": "2023-02-19 10:43:48+00:00",
    "pushed_at": "2021-03-01 17:14:30+00:00",
    "fork": false,
    "stargazers_count": 42,
    "watchers_count": 42,
    "forks_count": 8,
    "open_issues_count": 14,
    "license": "Other",
    "topics": []
  },
  {
    "org": "coralproject",
    "name": "talk-deprecated",
    "full_name": "coralproject/talk-deprecated",
    "homepage": "https://coralproject.net/",
    "description": "Configuration and installation files for Talk system.",
    "language": "Shell",
    "created_at": "2016-07-15 05:29:28+00:00",
    "updated_at": "2016-10-31 18:50:41+00:00",
    "pushed_at": "2016-10-28 18:38:30+00:00",
    "fork": false,
    "stargazers_count": 1,
    "watchers_count": 1,
    "forks_count": 2,
    "open_issues_count": 2,
    "license": "Other",
    "topics": []
  },
  {
    "org": "coralproject",
    "name": "shelf-poc",
    "full_name": "coralproject/shelf-poc",
    "homepage": null,
    "description": "POC functionality for shelf, a view engine sitting between sponge and xenia.",
    "language": "Go",
    "created_at": "2016-07-15 18:27:38+00:00",
    "updated_at": "2018-11-17 22:55:54+00:00",
    "pushed_at": "2016-09-27 21:44:52+00:00",
    "fork": false,
    "stargazers_count": 1,
    "watchers_count": 1,
    "forks_count": 1,
    "open_issues_count": 0,
    "license": null,
    "topics": []
  },
  {
    "org": "coralproject",
    "name": "heroku-buildpack-coralproject",
    "full_name": "coralproject/heroku-buildpack-coralproject",
    "homepage": null,
    "description": null,
    "language": "Shell",
    "created_at": "2016-08-15 16:03:52+00:00",
    "updated_at": "2016-09-02 05:18:30+00:00",
    "pushed_at": "2016-10-12 21:03:46+00:00",
    "fork": false,
    "stargazers_count": 1,
    "watchers_count": 1,
    "forks_count": 3,
    "open_issues_count": 0,
    "license": "Other",
    "topics": []
  },
  {
    "org": "coralproject",
    "name": "cayley",
    "full_name": "coralproject/cayley",
    "homepage": "",
    "description": "An open-source graph database",
    "language": "Go",
    "created_at": "2016-08-17 19:01:06+00:00",
    "updated_at": "2016-10-05 14:27:17+00:00",
    "pushed_at": "2016-10-14 20:00:41+00:00",
    "fork": true,
    "stargazers_count": 2,
    "watchers_count": 2,
    "forks_count": 1,
    "open_issues_count": 0,
    "license": "Apache License 2.0",
    "topics": []
  },
  {
    "org": "coralproject",
    "name": "nlp_worker",
    "full_name": "coralproject/nlp_worker",
    "homepage": null,
    "description": "Worker to process text",
    "language": "Makefile",
    "created_at": "2016-09-02 21:43:39+00:00",
    "updated_at": "2017-01-20 19:38:50+00:00",
    "pushed_at": "2016-09-02 21:43:53+00:00",
    "fork": false,
    "stargazers_count": 0,
    "watchers_count": 0,
    "forks_count": 1,
    "open_issues_count": 0,
    "license": null,
    "topics": []
  },
  {
    "org": "coralproject",
    "name": "scheduler",
    "full_name": "coralproject/scheduler",
    "homepage": null,
    "description": "POC for scheduler",
    "language": "Go",
    "created_at": "2016-09-02 22:14:12+00:00",
    "updated_at": "2017-01-20 19:42:47+00:00",
    "pushed_at": "2016-09-02 22:14:21+00:00",
    "fork": false,
    "stargazers_count": 0,
    "watchers_count": 0,
    "forks_count": 1,
    "open_issues_count": 0,
    "license": null,
    "topics": []
  },
  {
    "org": "coralproject",
    "name": "coral-auth",
    "full_name": "coralproject/coral-auth",
    "homepage": "https://www.coralproject.net",
    "description": "Open source identity/authorization system, built for The Coral Project's products. Supports OpenID and OAuth 2.0 (Facebook, Twitter, etc) through Passport.js",
    "language": "JavaScript",
    "created_at": "2016-09-15 14:14:47+00:00",
    "updated_at": "2023-01-28 09:29:01+00:00",
    "pushed_at": "2020-03-31 16:32:49+00:00",
    "fork": false,
    "stargazers_count": 2,
    "watchers_count": 2,
    "forks_count": 1,
    "open_issues_count": 1,
    "license": "Other",
    "topics": []
  },
  {
    "org": "coralproject",
    "name": "ask-install",
    "full_name": "coralproject/ask-install",
    "homepage": "https://docs.coralproject.net/products/ask/",
    "description": "Installer for Ask ",
    "language": "Go",
    "created_at": "2016-10-19 15:06:56+00:00",
    "updated_at": "2022-11-26 04:02:07+00:00",
    "pushed_at": "2018-10-23 16:52:50+00:00",
    "fork": false,
    "stargazers_count": 20,
    "watchers_count": 20,
    "forks_count": 5,
    "open_issues_count": 1,
    "license": null,
    "topics": []
  },
  {
    "org": "coralproject",
    "name": "talk",
    "full_name": "coralproject/talk",
    "homepage": "https://coralproject.net",
    "description": "A better commenting experience from Vox Media",
    "language": "TypeScript",
    "created_at": "2016-10-31 16:14:05+00:00",
    "updated_at": "2025-07-24 01:26:53+00:00",
    "pushed_at": "2025-07-17 15:52:20+00:00",
    "fork": false,
    "stargazers_count": 1949,
    "watchers_count": 1949,
    "forks_count": 361,
    "open_issues_count": 40,
    "license": "Other",
    "topics": [
      "comments",
      "comments-widget",
      "graphql",
      "javascript",
      "journalism",
      "nodejs",
      "react",
      "typescript"
    ]
  },
  {
    "org": "coralproject",
    "name": "ask-slack-bouncer",
    "full_name": "coralproject/ask-slack-bouncer",
    "homepage": null,
    "description": "A slack bouncing server which proxies an endpoint and allows messages to be relayed.",
    "language": "JavaScript",
    "created_at": "2016-11-03 22:53:24+00:00",
    "updated_at": "2017-10-25 22:06:55+00:00",
    "pushed_at": "2016-11-04 17:51:21+00:00",
    "fork": true,
    "stargazers_count": 0,
    "watchers_count": 0,
    "forks_count": 1,
    "open_issues_count": 0,
    "license": null,
    "topics": []
  },
  {
    "org": "coralproject",
    "name": "ask-wp-plugin",
    "full_name": "coralproject/ask-wp-plugin",
    "homepage": "",
    "description": "A WordPress plugin for Ask",
    "language": "PHP",
    "created_at": "2016-12-22 15:07:41+00:00",
    "updated_at": "2023-08-27 11:24:45+00:00",
    "pushed_at": "2019-02-01 15:10:48+00:00",
    "fork": false,
    "stargazers_count": 11,
    "watchers_count": 11,
    "forks_count": 7,
    "open_issues_count": 3,
    "license": null,
    "topics": []
  },
  {
    "org": "coralproject",
    "name": "talk-install",
    "full_name": "coralproject/talk-install",
    "homepage": "",
    "description": "[DEPRECATED] Use \"Deploy to Heroku\" button on https://github.com/coralproject/talk",
    "language": "JavaScript",
    "created_at": "2016-12-23 17:44:01+00:00",
    "updated_at": "2017-08-28 21:37:21+00:00",
    "pushed_at": "2017-08-28 21:37:45+00:00",
    "fork": false,
    "stargazers_count": 0,
    "watchers_count": 0,
    "forks_count": 2,
    "open_issues_count": 0,
    "license": "Other",
    "topics": []
  },
  {
    "org": "coralproject",
    "name": "coral-plugin-trust",
    "full_name": "coralproject/coral-plugin-trust",
    "homepage": "",
    "description": "Trust Plugin for Talk enables User activity tracking and automated behaviours to assist moderators.",
    "language": "JavaScript",
    "created_at": "2017-04-24 15:45:30+00:00",
    "updated_at": "2017-05-02 21:02:44+00:00",
    "pushed_at": "2017-06-06 15:52:39+00:00",
    "fork": false,
    "stargazers_count": 1,
    "watchers_count": 1,
    "forks_count": 1,
    "open_issues_count": 1,
    "license": "Other",
    "topics": []
  },
  {
    "org": "coralproject",
    "name": "talk-go",
    "full_name": "coralproject/talk-go",
    "homepage": null,
    "description": "Coral API Bindings for GO",
    "language": "Go",
    "created_at": "2017-06-07 20:32:53+00:00",
    "updated_at": "2017-06-07 20:33:30+00:00",
    "pushed_at": "2017-06-07 20:34:45+00:00",
    "fork": false,
    "stargazers_count": 0,
    "watchers_count": 0,
    "forks_count": 1,
    "open_issues_count": 0,
    "license": null,
    "topics": []
  },
  {
    "org": "coralproject",
    "name": "talk-importer-disqus",
    "full_name": "coralproject/talk-importer-disqus",
    "homepage": "",
    "description": "[DEPRECATED] Please refer to https://github.com/coralproject/talk-importer-livefyre",
    "language": "JavaScript",
    "created_at": "2017-06-09 00:12:39+00:00",
    "updated_at": "2023-01-28 21:13:37+00:00",
    "pushed_at": "2018-01-18 23:59:40+00:00",
    "fork": false,
    "stargazers_count": 3,
    "watchers_count": 3,
    "forks_count": 1,
    "open_issues_count": 4,
    "license": "Other",
    "topics": [
      "comments",
      "data",
      "import"
    ]
  },
  {
    "org": "coralproject",
    "name": "talk-wp-plugin",
    "full_name": "coralproject/talk-wp-plugin",
    "homepage": "",
    "description": "WordPress plugin for Coral",
    "language": "PHP",
    "created_at": "2017-06-13 00:42:10+00:00",
    "updated_at": "2024-01-22 17:43:44+00:00",
    "pushed_at": "2024-01-22 17:44:37+00:00",
    "fork": false,
    "stargazers_count": 22,
    "watchers_count": 22,
    "forks_count": 12,
    "open_issues_count": 2,
    "license": null,
    "topics": []
  },
  {
    "org": "coralproject",
    "name": "talk-plugin-toxicity",
    "full_name": "coralproject/talk-plugin-toxicity",
    "homepage": null,
    "description": null,
    "language": "JavaScript",
    "created_at": "2017-06-27 15:54:12+00:00",
    "updated_at": "2023-01-28 20:05:31+00:00",
    "pushed_at": "2017-07-25 16:03:45+00:00",
    "fork": false,
    "stargazers_count": 1,
    "watchers_count": 1,
    "forks_count": 1,
    "open_issues_count": 0,
    "license": null,
    "topics": []
  },
  {
    "org": "coralproject",
    "name": "talk-recipes",
    "full_name": "coralproject/talk-recipes",
    "homepage": "https://coralproject.net/",
    "description": "Recipes to use with The Coral Project's Talk",
    "language": "JavaScript",
    "created_at": "2017-07-10 20:44:25+00:00",
    "updated_at": "2022-03-21 12:10:23+00:00",
    "pushed_at": "2022-07-07 06:57:22+00:00",
    "fork": false,
    "stargazers_count": 12,
    "watchers_count": 12,
    "forks_count": 9,
    "open_issues_count": 2,
    "license": null,
    "topics": []
  },
  {
    "org": "coralproject",
    "name": "coralcert",
    "full_name": "coralproject/coralcert",
    "homepage": null,
    "description": "Secret Generation for The Coral Project's Talk product.",
    "language": "Go",
    "created_at": "2017-08-04 01:49:23+00:00",
    "updated_at": "2019-10-02 18:39:35+00:00",
    "pushed_at": "2019-10-02 18:41:23+00:00",
    "fork": false,
    "stargazers_count": 1,
    "watchers_count": 1,
    "forks_count": 1,
    "open_issues_count": 0,
    "license": "Other",
    "topics": []
  },
  {
    "org": "coralproject",
    "name": "talk-framework-poc",
    "full_name": "coralproject/talk-framework-poc",
    "homepage": "",
    "description": "Proof of concept implementation of the Talk Framework. DO NOT USE, IN PROGRESS",
    "language": "TypeScript",
    "created_at": "2017-08-04 04:09:25+00:00",
    "updated_at": "2017-08-04 04:10:23+00:00",
    "pushed_at": "2018-02-03 18:23:49+00:00",
    "fork": false,
    "stargazers_count": 0,
    "watchers_count": 0,
    "forks_count": 1,
    "open_issues_count": 0,
    "license": null,
    "topics": []
  },
  {
    "org": "coralproject",
    "name": "homebrew-stable",
    "full_name": "coralproject/homebrew-stable",
    "homepage": null,
    "description": "Homebrew tap for The Coral Project",
    "language": "Ruby",
    "created_at": "2017-09-07 22:02:47+00:00",
    "updated_at": "2019-10-02 19:10:50+00:00",
    "pushed_at": "2019-10-02 19:10:48+00:00",
    "fork": false,
    "stargazers_count": 0,
    "watchers_count": 0,
    "forks_count": 1,
    "open_issues_count": 0,
    "license": "Apache License 2.0",
    "topics": []
  },
  {
    "org": "coralproject",
    "name": "eslint-config-talk",
    "full_name": "coralproject/eslint-config-talk",
    "homepage": null,
    "description": "Provides eslint config for plugin development",
    "language": "JavaScript",
    "created_at": "2017-09-26 12:26:48+00:00",
    "updated_at": "2017-12-05 02:23:55+00:00",
    "pushed_at": "2018-01-25 18:20:11+00:00",
    "fork": false,
    "stargazers_count": 1,
    "watchers_count": 1,
    "forks_count": 1,
    "open_issues_count": 0,
    "license": "Other",
    "topics": []
  },
  {
    "org": "coralproject",
    "name": "slack-bouncer",
    "full_name": "coralproject/slack-bouncer",
    "homepage": null,
    "description": "A Slack Application for Talk that relays interactive messages to enable moderation through a Slack channel.",
    "language": "JavaScript",
    "created_at": "2017-10-25 22:08:20+00:00",
    "updated_at": "2022-03-23 21:15:59+00:00",
    "pushed_at": "2023-07-11 00:58:04+00:00",
    "fork": false,
    "stargazers_count": 2,
    "watchers_count": 2,
    "forks_count": 2,
    "open_issues_count": 17,
    "license": "Other",
    "topics": []
  },
  {
    "org": "coralproject",
    "name": "slack-bouncer-functions",
    "full_name": "coralproject/slack-bouncer-functions",
    "homepage": null,
    "description": "A Google Cloud Function Publisher that publishes comments sent to it to a Pub/Sub topic.",
    "language": "TypeScript",
    "created_at": "2017-10-26 00:46:30+00:00",
    "updated_at": "2021-07-26 18:08:08+00:00",
    "pushed_at": "2023-07-12 02:34:30+00:00",
    "fork": false,
    "stargazers_count": 0,
    "watchers_count": 0,
    "forks_count": 1,
    "open_issues_count": 13,
    "license": "Other",
    "topics": []
  },
  {
    "org": "coralproject",
    "name": "talk-plugin-slack-bouncer",
    "full_name": "coralproject/talk-plugin-slack-bouncer",
    "homepage": null,
    "description": null,
    "language": "JavaScript",
    "created_at": "2017-10-26 00:58:14+00:00",
    "updated_at": "2022-03-21 12:10:23+00:00",
    "pushed_at": "2023-07-11 07:41:57+00:00",
    "fork": false,
    "stargazers_count": 0,
    "watchers_count": 0,
    "forks_count": 2,
    "open_issues_count": 5,
    "license": "Other",
    "topics": []
  },
  {
    "org": "coralproject",
    "name": "talk-bench",
    "full_name": "coralproject/talk-bench",
    "homepage": null,
    "description": "A script to benchmark Talk",
    "language": "Java",
    "created_at": "2017-11-01 14:16:10+00:00",
    "updated_at": "2017-11-01 14:18:30+00:00",
    "pushed_at": "2017-12-10 00:11:56+00:00",
    "fork": false,
    "stargazers_count": 0,
    "watchers_count": 0,
    "forks_count": 1,
    "open_issues_count": 0,
    "license": null,
    "topics": []
  },
  {
    "org": "coralproject",
    "name": "graphql-ast-tools",
    "full_name": "coralproject/graphql-ast-tools",
    "homepage": null,
    "description": "Tools for the GraphQL Abstract Syntax Tree",
    "language": "TypeScript",
    "created_at": "2017-12-05 16:19:04+00:00",
    "updated_at": "2021-04-06 17:00:08+00:00",
    "pushed_at": "2017-12-07 18:40:49+00:00",
    "fork": false,
    "stargazers_count": 5,
    "watchers_count": 5,
    "forks_count": 2,
    "open_issues_count": 0,
    "license": "Other",
    "topics": [
      "graphql"
    ]
  },
  {
    "org": "coralproject",
    "name": "talk-importer",
    "full_name": "coralproject/talk-importer",
    "homepage": "",
    "description": "Import tool to migrate comments into Talk",
    "language": "JavaScript",
    "created_at": "2018-01-11 22:15:54+00:00",
    "updated_at": "2023-01-28 15:42:33+00:00",
    "pushed_at": "2019-11-01 22:39:34+00:00",
    "fork": false,
    "stargazers_count": 2,
    "watchers_count": 2,
    "forks_count": 3,
    "open_issues_count": 2,
    "license": "Apache License 2.0",
    "topics": []
  },
  {
    "org": "coralproject",
    "name": "talk-plugin-custom-asset-id",
    "full_name": "coralproject/talk-plugin-custom-asset-id",
    "homepage": null,
    "description": "Custom Asset ID Plugin for The Coral Project's Talk",
    "language": "JavaScript",
    "created_at": "2018-01-12 01:22:00+00:00",
    "updated_at": "2018-04-16 14:58:38+00:00",
    "pushed_at": "2021-06-16 20:55:07+00:00",
    "fork": false,
    "stargazers_count": 0,
    "watchers_count": 0,
    "forks_count": 1,
    "open_issues_count": 0,
    "license": "Other",
    "topics": []
  },
  {
    "org": "coralproject",
    "name": "talk-plugin-pride",
    "full_name": "coralproject/talk-plugin-pride",
    "homepage": null,
    "description": null,
    "language": "JavaScript",
    "created_at": "2018-03-06 17:07:20+00:00",
    "updated_at": "2018-03-23 17:02:03+00:00",
    "pushed_at": "2018-03-09 17:17:54+00:00",
    "fork": false,
    "stargazers_count": 2,
    "watchers_count": 2,
    "forks_count": 1,
    "open_issues_count": 0,
    "license": null,
    "topics": []
  },
  {
    "org": "coralproject",
    "name": "awesome-talk",
    "full_name": "coralproject/awesome-talk",
    "homepage": null,
    "description": " A curated list of useful resources for Talk",
    "language": null,
    "created_at": "2018-03-08 15:21:30+00:00",
    "updated_at": "2018-09-25 14:26:07+00:00",
    "pushed_at": "2018-03-08 15:29:00+00:00",
    "fork": false,
    "stargazers_count": 1,
    "watchers_count": 1,
    "forks_count": 1,
    "open_issues_count": 0,
    "license": null,
    "topics": []
  },
  {
    "org": "coralproject",
    "name": "talk-token-example",
    "full_name": "coralproject/talk-token-example",
    "homepage": null,
    "description": "Example application designed to broker tokens for Talk.",
    "language": "JavaScript",
    "created_at": "2018-03-09 04:30:40+00:00",
    "updated_at": "2025-03-21 13:42:03+00:00",
    "pushed_at": "2018-08-16 17:48:34+00:00",
    "fork": false,
    "stargazers_count": 3,
    "watchers_count": 3,
    "forks_count": 2,
    "open_issues_count": 0,
    "license": "Other",
    "topics": []
  },
  {
    "org": "coralproject",
    "name": "ci",
    "full_name": "coralproject/ci",
    "homepage": null,
    "description": "Build image for integration tests.",
    "language": null,
    "created_at": "2018-03-13 18:15:55+00:00",
    "updated_at": "2018-05-29 17:21:23+00:00",
    "pushed_at": "2018-05-29 17:21:21+00:00",
    "fork": false,
    "stargazers_count": 0,
    "watchers_count": 0,
    "forks_count": 1,
    "open_issues_count": 0,
    "license": null,
    "topics": []
  },
  {
    "org": "coralproject",
    "name": "talk-plugin-asset-manager-example",
    "full_name": "coralproject/talk-plugin-asset-manager-example",
    "homepage": null,
    "description": null,
    "language": "JavaScript",
    "created_at": "2018-03-15 18:34:26+00:00",
    "updated_at": "2018-03-15 18:37:23+00:00",
    "pushed_at": "2018-03-15 18:37:22+00:00",
    "fork": false,
    "stargazers_count": 0,
    "watchers_count": 0,
    "forks_count": 1,
    "open_issues_count": 0,
    "license": "Other",
    "topics": []
  },
  {
    "org": "coralproject",
    "name": "talk-devtools-extension",
    "full_name": "coralproject/talk-devtools-extension",
    "homepage": "http://coralproject.net",
    "description": "Devtools for Talk",
    "language": "HTML",
    "created_at": "2018-03-17 23:43:28+00:00",
    "updated_at": "2018-04-26 16:19:17+00:00",
    "pushed_at": "2018-03-20 17:50:54+00:00",
    "fork": false,
    "stargazers_count": 2,
    "watchers_count": 2,
    "forks_count": 1,
    "open_issues_count": 0,
    "license": null,
    "topics": [
      "chrome",
      "coralproject",
      "devtools",
      "firefox",
      "talk"
    ]
  },
  {
    "org": "coralproject",
    "name": "gql",
    "full_name": "coralproject/gql",
    "homepage": "",
    "description": "Tools for working with GraphQL documents",
    "language": "JavaScript",
    "created_at": "2018-03-20 17:09:56+00:00",
    "updated_at": "2019-03-11 08:30:32+00:00",
    "pushed_at": "2018-05-28 16:55:52+00:00",
    "fork": true,
    "stargazers_count": 0,
    "watchers_count": 0,
    "forks_count": 3,
    "open_issues_count": 1,
    "license": "MIT License",
    "topics": []
  },
  {
    "org": "coralproject",
    "name": "talk-plugin-auth-checkbox",
    "full_name": "coralproject/talk-plugin-auth-checkbox",
    "homepage": "",
    "description": "Adds a checkbox that has to be ticked to Coral's auth plugin. Useful for accepting privacy policies.",
    "language": "JavaScript",
    "created_at": "2018-03-26 16:09:15+00:00",
    "updated_at": "2018-06-20 22:01:43+00:00",
    "pushed_at": "2018-06-20 22:01:42+00:00",
    "fork": false,
    "stargazers_count": 0,
    "watchers_count": 0,
    "forks_count": 2,
    "open_issues_count": 0,
    "license": "Other",
    "topics": []
  },
  {
    "org": "coralproject",
    "name": "patched",
    "full_name": "coralproject/patched",
    "homepage": "",
    "description": "Patched npm packages that we use in our projects",
    "language": null,
    "created_at": "2018-06-27 18:39:05+00:00",
    "updated_at": "2018-06-27 21:01:35+00:00",
    "pushed_at": "2021-01-28 13:48:09+00:00",
    "fork": false,
    "stargazers_count": 0,
    "watchers_count": 0,
    "forks_count": 1,
    "open_issues_count": 0,
    "license": null,
    "topics": []
  },
  {
    "org": "coralproject",
    "name": "bunyan-raven",
    "full_name": "coralproject/bunyan-raven",
    "homepage": "",
    "description": "Make raven-node and node-bunyan friends. : )",
    "language": "JavaScript",
    "created_at": "2018-08-16 15:30:31+00:00",
    "updated_at": "2018-08-16 15:30:56+00:00",
    "pushed_at": "2017-02-22 06:03:20+00:00",
    "fork": true,
    "stargazers_count": 0,
    "watchers_count": 0,
    "forks_count": 1,
    "open_issues_count": 0,
    "license": null,
    "topics": []
  },
  {
    "org": "coralproject",
    "name": "rte",
    "full_name": "coralproject/rte",
    "homepage": null,
    "description": "A Lightweight Rich Text Editor based on React",
    "language": "TypeScript",
    "created_at": "2018-08-24 08:02:11+00:00",
    "updated_at": "2024-02-15 01:35:23+00:00",
    "pushed_at": "2023-07-18 22:03:56+00:00",
    "fork": false,
    "stargazers_count": 6,
    "watchers_count": 6,
    "forks_count": 3,
    "open_issues_count": 26,
    "license": "Other",
    "topics": [
      "react",
      "rich-text-editor",
      "rte",
      "typescript"
    ]
  },
  {
    "org": "coralproject",
    "name": "talk-plugin-prom",
    "full_name": "coralproject/talk-plugin-prom",
    "homepage": null,
    "description": "Prometheus exporter for Talk",
    "language": "JavaScript",
    "created_at": "2018-09-04 17:04:28+00:00",
    "updated_at": "2022-03-21 12:10:25+00:00",
    "pushed_at": "2023-10-02 18:22:45+00:00",
    "fork": false,
    "stargazers_count": 4,
    "watchers_count": 4,
    "forks_count": 2,
    "open_issues_count": 8,
    "license": "Other",
    "topics": [
      "coralproject",
      "metrics",
      "observability",
      "prometheus",
      "talk"
    ]
  },
  {
    "org": "coralproject",
    "name": "pushgateway",
    "full_name": "coralproject/pushgateway",
    "homepage": null,
    "description": "push acceptor for ephemeral and batch jobs",
    "language": "Go",
    "created_at": "2018-09-11 15:16:03+00:00",
    "updated_at": "2019-05-28 18:16:08+00:00",
    "pushed_at": "2018-09-11 15:16:34+00:00",
    "fork": true,
    "stargazers_count": 1,
    "watchers_count": 1,
    "forks_count": 0,
    "open_issues_count": 0,
    "license": "Apache License 2.0",
    "topics": []
  },
  {
    "org": "coralproject",
    "name": "DefinitelyTyped",
    "full_name": "coralproject/DefinitelyTyped",
    "homepage": "http://definitelytyped.org/",
    "description": "The repository for high quality TypeScript type definitions.",
    "language": "TypeScript",
    "created_at": "2018-09-21 03:47:07+00:00",
    "updated_at": "2020-08-05 00:01:28+00:00",
    "pushed_at": "2020-08-05 00:00:54+00:00",
    "fork": true,
    "stargazers_count": 1,
    "watchers_count": 1,
    "forks_count": 0,
    "open_issues_count": 0,
    "license": "Other",
    "topics": []
  },
  {
    "org": "coralproject",
    "name": "talk-plugin-comment-count",
    "full_name": "coralproject/talk-plugin-comment-count",
    "homepage": null,
    "description": "A plugin for Talk that allows seamless integration of the comment count across your site.",
    "language": "JavaScript",
    "created_at": "2018-10-18 19:21:59+00:00",
    "updated_at": "2019-04-23 21:34:43+00:00",
    "pushed_at": "2019-04-23 21:37:10+00:00",
    "fork": false,
    "stargazers_count": 1,
    "watchers_count": 1,
    "forks_count": 3,
    "open_issues_count": 0,
    "license": "Other",
    "topics": []
  },
  {
    "org": "coralproject",
    "name": "readthedocs.org",
    "full_name": "coralproject/readthedocs.org",
    "homepage": "https://readthedocs.org/",
    "description": "The source code that powers readthedocs.org",
    "language": "Python",
    "created_at": "2018-10-19 20:21:01+00:00",
    "updated_at": "2018-11-13 02:02:32+00:00",
    "pushed_at": "2018-11-13 02:02:24+00:00",
    "fork": true,
    "stargazers_count": 0,
    "watchers_count": 0,
    "forks_count": 0,
    "open_issues_count": 0,
    "license": "MIT License",
    "topics": []
  },
  {
    "org": "coralproject",
    "name": "talk-plugin-toxic-comments-study",
    "full_name": "coralproject/talk-plugin-toxic-comments-study",
    "homepage": null,
    "description": null,
    "language": "JavaScript",
    "created_at": "2018-11-02 20:27:24+00:00",
    "updated_at": "2023-01-28 19:43:17+00:00",
    "pushed_at": "2018-11-06 19:57:55+00:00",
    "fork": false,
    "stargazers_count": 0,
    "watchers_count": 0,
    "forks_count": 1,
    "open_issues_count": 0,
    "license": null,
    "topics": []
  },
  {
    "org": "coralproject",
    "name": "node-bunyan-prettystream",
    "full_name": "coralproject/node-bunyan-prettystream",
    "homepage": null,
    "description": "A stream implementation of the bunyan cli tool's pretty printing capabilities",
    "language": "JavaScript",
    "created_at": "2019-01-16 22:46:39+00:00",
    "updated_at": "2019-01-16 23:04:40+00:00",
    "pushed_at": "2019-01-16 23:04:39+00:00",
    "fork": true,
    "stargazers_count": 0,
    "watchers_count": 0,
    "forks_count": 1,
    "open_issues_count": 0,
    "license": null,
    "topics": []
  },
  {
    "org": "coralproject",
    "name": "npm-run-all",
    "full_name": "coralproject/npm-run-all",
    "homepage": "",
    "description": "A CLI tool to run multiple npm-scripts in parallel or sequential.",
    "language": "JavaScript",
    "created_at": "2019-05-28 21:55:10+00:00",
    "updated_at": "2019-06-04 20:47:20+00:00",
    "pushed_at": "2019-06-04 20:47:17+00:00",
    "fork": true,
    "stargazers_count": 0,
    "watchers_count": 0,
    "forks_count": 1,
    "open_issues_count": 0,
    "license": "MIT License",
    "topics": []
  },
  {
    "org": "coralproject",
    "name": "permit",
    "full_name": "coralproject/permit",
    "homepage": "",
    "description": "An unopinionated authentication library for building Node.js APIs.",
    "language": "JavaScript",
    "created_at": "2019-05-31 20:28:11+00:00",
    "updated_at": "2019-05-31 21:37:31+00:00",
    "pushed_at": "2018-07-17 20:43:15+00:00",
    "fork": true,
    "stargazers_count": 0,
    "watchers_count": 0,
    "forks_count": 1,
    "open_issues_count": 0,
    "license": "MIT License",
    "topics": []
  },
  {
    "org": "coralproject",
    "name": "plugin-plugins",
    "full_name": "coralproject/plugin-plugins",
    "homepage": "",
    "description": "plugins plugin for oclif",
    "language": "TypeScript",
    "created_at": "2019-09-25 20:34:01+00:00",
    "updated_at": "2022-03-21 12:10:26+00:00",
    "pushed_at": "2023-09-04 17:15:48+00:00",
    "fork": true,
    "stargazers_count": 0,
    "watchers_count": 0,
    "forks_count": 1,
    "open_issues_count": 6,
    "license": "MIT License",
    "topics": []
  },
  {
    "org": "coralproject",
    "name": "coral-cli",
    "full_name": "coralproject/coral-cli",
    "homepage": null,
    "description": "CLI to interact with Coral",
    "language": "TypeScript",
    "created_at": "2019-10-02 16:41:01+00:00",
    "updated_at": "2023-02-19 06:11:33+00:00",
    "pushed_at": "2023-07-24 12:23:17+00:00",
    "fork": false,
    "stargazers_count": 3,
    "watchers_count": 3,
    "forks_count": 2,
    "open_issues_count": 17,
    "license": null,
    "topics": []
  },
  {
    "org": "coralproject",
    "name": "coral-cli-command",
    "full_name": "coralproject/coral-cli-command",
    "homepage": null,
    "description": "base class for Coral CLI commands",
    "language": "TypeScript",
    "created_at": "2019-10-02 16:41:56+00:00",
    "updated_at": "2022-02-09 18:10:51+00:00",
    "pushed_at": "2023-09-11 02:46:55+00:00",
    "fork": false,
    "stargazers_count": 1,
    "watchers_count": 1,
    "forks_count": 2,
    "open_issues_count": 25,
    "license": "Other",
    "topics": []
  },
  {
    "org": "coralproject",
    "name": "metascraper",
    "full_name": "coralproject/metascraper",
    "homepage": "https://metascraper.js.org",
    "description": "Scrape data from websites using Open Graph metadata, regular HTML metadata, and a series of fallbacks.",
    "language": null,
    "created_at": "2019-11-08 21:45:41+00:00",
    "updated_at": "2022-02-09 18:07:09+00:00",
    "pushed_at": "2019-11-08 21:34:17+00:00",
    "fork": true,
    "stargazers_count": 1,
    "watchers_count": 1,
    "forks_count": 2,
    "open_issues_count": 0,
    "license": "MIT License",
    "topics": []
  },
  {
    "org": "coralproject",
    "name": "package-version-lint",
    "full_name": "coralproject/package-version-lint",
    "homepage": null,
    "description": "Linter for package.json and package-lock.json files.",
    "language": "TypeScript",
    "created_at": "2020-03-18 22:31:11+00:00",
    "updated_at": "2020-12-29 18:28:22+00:00",
    "pushed_at": "2023-07-19 00:54:36+00:00",
    "fork": false,
    "stargazers_count": 0,
    "watchers_count": 0,
    "forks_count": 1,
    "open_issues_count": 6,
    "license": "Other",
    "topics": []
  },
  {
    "org": "coralproject",
    "name": "webhook-example",
    "full_name": "coralproject/webhook-example",
    "homepage": null,
    "description": "An example application used for webhooks with Coral",
    "language": "JavaScript",
    "created_at": "2020-03-23 21:34:15+00:00",
    "updated_at": "2020-03-23 21:34:26+00:00",
    "pushed_at": "2024-03-26 15:50:38+00:00",
    "fork": false,
    "stargazers_count": 0,
    "watchers_count": 0,
    "forks_count": 1,
    "open_issues_count": 1,
    "license": null,
    "topics": []
  },
  {
    "org": "coralproject",
    "name": "events",
    "full_name": "coralproject/events",
    "homepage": null,
    "description": "Events SDK for NodeJS for interacting with Coral events.",
    "language": "TypeScript",
    "created_at": "2020-03-23 23:22:28+00:00",
    "updated_at": "2020-12-29 18:48:12+00:00",
    "pushed_at": "2023-07-19 00:54:57+00:00",
    "fork": false,
    "stargazers_count": 0,
    "watchers_count": 0,
    "forks_count": 1,
    "open_issues_count": 18,
    "license": "Other",
    "topics": []
  },
  {
    "org": "coralproject",
    "name": "tstdoc",
    "full_name": "coralproject/tstdoc",
    "homepage": null,
    "description": "Type documentation system that assists with Typescript interface documentation.",
    "language": "TypeScript",
    "created_at": "2020-04-16 15:42:48+00:00",
    "updated_at": "2020-04-16 16:31:48+00:00",
    "pushed_at": "2023-07-18 21:45:46+00:00",
    "fork": false,
    "stargazers_count": 0,
    "watchers_count": 0,
    "forks_count": 1,
    "open_issues_count": 16,
    "license": "Other",
    "topics": []
  },
  {
    "org": "coralproject",
    "name": "mdx-book",
    "full_name": "coralproject/mdx-book",
    "homepage": null,
    "description": "MDX Book is `docz` inspired documentation generator",
    "language": "TypeScript",
    "created_at": "2020-08-12 18:08:14+00:00",
    "updated_at": "2020-08-13 18:53:50+00:00",
    "pushed_at": "2020-08-13 18:53:47+00:00",
    "fork": false,
    "stargazers_count": 0,
    "watchers_count": 0,
    "forks_count": 1,
    "open_issues_count": 0,
    "license": "Other",
    "topics": []
  },
  {
    "org": "coralproject",
    "name": "apollo-server",
    "full_name": "coralproject/apollo-server",
    "homepage": "https://www.apollographql.com/docs/apollo-server/",
    "description": "\ud83c\udf0d GraphQL server for Express, Connect, Hapi, Koa and more",
    "language": null,
    "created_at": "2020-12-03 04:28:52+00:00",
    "updated_at": "2020-12-03 04:28:56+00:00",
    "pushed_at": "2020-12-02 00:07:46+00:00",
    "fork": true,
    "stargazers_count": 0,
    "watchers_count": 0,
    "forks_count": 0,
    "open_issues_count": 0,
    "license": "MIT License",
    "topics": []
  },
  {
    "org": "coralproject",
    "name": "graphql-docs",
    "full_name": "coralproject/graphql-docs",
    "homepage": null,
    "description": "GraphQL documentation explorer",
    "language": "JavaScript",
    "created_at": "2020-12-04 17:18:58+00:00",
    "updated_at": "2022-02-09 18:08:49+00:00",
    "pushed_at": "2020-12-07 12:27:13+00:00",
    "fork": true,
    "stargazers_count": 1,
    "watchers_count": 1,
    "forks_count": 1,
    "open_issues_count": 0,
    "license": "MIT License",
    "topics": []
  },
  {
    "org": "coralproject",
    "name": "coral-counts",
    "full_name": "coralproject/coral-counts",
    "homepage": null,
    "description": "A tool to update comment counts after a import.",
    "language": "Go",
    "created_at": "2021-01-21 06:50:37+00:00",
    "updated_at": "2022-03-21 12:10:29+00:00",
    "pushed_at": "2023-09-11 22:17:43+00:00",
    "fork": false,
    "stargazers_count": 0,
    "watchers_count": 0,
    "forks_count": 1,
    "open_issues_count": 7,
    "license": null,
    "topics": []
  },
  {
    "org": "coralproject",
    "name": "coral-importer",
    "full_name": "coralproject/coral-importer",
    "homepage": null,
    "description": "A CLI tool that imports comment exports from other providers into Coral.",
    "language": "Go",
    "created_at": "2021-01-21 23:39:44+00:00",
    "updated_at": "2022-05-09 14:28:00+00:00",
    "pushed_at": "2023-11-30 01:02:54+00:00",
    "fork": false,
    "stargazers_count": 0,
    "watchers_count": 0,
    "forks_count": 3,
    "open_issues_count": 10,
    "license": null,
    "topics": []
  },
  {
    "org": "coralproject",
    "name": "coral-cli-plugin-simulate-activity",
    "full_name": "coralproject/coral-cli-plugin-simulate-activity",
    "homepage": null,
    "description": null,
    "language": "TypeScript",
    "created_at": "2021-02-05 13:37:52+00:00",
    "updated_at": "2021-03-29 21:25:58+00:00",
    "pushed_at": "2021-02-05 14:57:32+00:00",
    "fork": false,
    "stargazers_count": 0,
    "watchers_count": 0,
    "forks_count": 1,
    "open_issues_count": 0,
    "license": null,
    "topics": []
  },
  {
    "org": "coralproject",
    "name": "coral-party",
    "full_name": "coralproject/coral-party",
    "homepage": null,
    "description": null,
    "language": "TypeScript",
    "created_at": "2021-02-17 19:34:14+00:00",
    "updated_at": "2024-10-15 18:04:13+00:00",
    "pushed_at": "2024-10-15 18:04:09+00:00",
    "fork": false,
    "stargazers_count": 1,
    "watchers_count": 1,
    "forks_count": 0,
    "open_issues_count": 0,
    "license": null,
    "topics": []
  },
  {
    "org": "coralproject",
    "name": "rudderstack-helm",
    "full_name": "coralproject/rudderstack-helm",
    "homepage": "",
    "description": "Open-source, warehouse-first Customer Data Pipeline and Segment-alternative. Collects and routes clickstream data and builds your customer data lake on your data warehouse.",
    "language": null,
    "created_at": "2021-06-29 21:44:08+00:00",
    "updated_at": "2021-06-29 21:44:09+00:00",
    "pushed_at": "2021-06-29 21:44:58+00:00",
    "fork": true,
    "stargazers_count": 0,
    "watchers_count": 0,
    "forks_count": 1,
    "open_issues_count": 0,
    "license": "MIT License",
    "topics": []
  },
  {
    "org": "coralproject",
    "name": "app-proxy",
    "full_name": "coralproject/app-proxy",
    "homepage": null,
    "description": "Example of Coral proxying a host page to embed comments in a progressive web app.",
    "language": "JavaScript",
    "created_at": "2024-03-28 19:52:28+00:00",
    "updated_at": "2024-03-28 19:52:53+00:00",
    "pushed_at": "2024-03-28 19:52:49+00:00",
    "fork": false,
    "stargazers_count": 0,
    "watchers_count": 0,
    "forks_count": 0,
    "open_issues_count": 0,
    "license": null,
    "topics": []
  }
]
